mlx_omni_server/__init__.py
mlx_omni_server/main.py
mlx_omni_server/routers.py
mlx_omni_server/chat/__init__.py
mlx_omni_server/chat/anthropic/__init__.py
mlx_omni_server/chat/anthropic/anthropic_messages_adapter.py
mlx_omni_server/chat/anthropic/anthropic_schema.py
mlx_omni_server/chat/anthropic/models_service.py
mlx_omni_server/chat/anthropic/router.py
mlx_omni_server/chat/anthropic/schema.py
mlx_omni_server/chat/mlx/__init__.py
mlx_omni_server/chat/mlx/chat_generator.py
mlx_omni_server/chat/mlx/core_types.py
mlx_omni_server/chat/mlx/logprobs_processor.py
mlx_omni_server/chat/mlx/model_types.py
mlx_omni_server/chat/mlx/models.py
mlx_omni_server/chat/mlx/outlines_logits_processor.py
mlx_omni_server/chat/mlx/prompt_cache.py
mlx_omni_server/chat/mlx/wrapper_cache.py
mlx_omni_server/chat/mlx/tools/__init__.py
mlx_omni_server/chat/mlx/tools/base_tools.py
mlx_omni_server/chat/mlx/tools/chat_template.py
mlx_omni_server/chat/mlx/tools/glm45_tools_parser.py
mlx_omni_server/chat/mlx/tools/hugging_face.py
mlx_omni_server/chat/mlx/tools/llama3.py
mlx_omni_server/chat/mlx/tools/mistral.py
mlx_omni_server/chat/mlx/tools/qwen3_moe_tools_parser.py
mlx_omni_server/chat/mlx/tools/thinking_decoder.py
mlx_omni_server/chat/openai/__init__.py
mlx_omni_server/chat/openai/openai_adapter.py
mlx_omni_server/chat/openai/router.py
mlx_omni_server/chat/openai/schema.py
mlx_omni_server/chat/openai/models/__init__.py
mlx_omni_server/chat/openai/models/models.py
mlx_omni_server/chat/openai/models/models_service.py
mlx_omni_server/chat/openai/models/schema.py
mlx_omni_server/embeddings/__init__.py
mlx_omni_server/embeddings/embeddings_service.py
mlx_omni_server/embeddings/router.py
mlx_omni_server/embeddings/schema.py
mlx_omni_server/images/__init__.py
mlx_omni_server/images/images.py
mlx_omni_server/images/images_service.py
mlx_omni_server/images/schema.py
mlx_omni_server/middleware/logging.py
mlx_omni_server/stt/__init__.py
mlx_omni_server/stt/schema.py
mlx_omni_server/stt/stt.py
mlx_omni_server-0.5.2.dist-info/METADATA
mlx_omni_server-0.5.2.dist-info/WHEEL
mlx_omni_server-0.5.2.dist-info/entry_points.txt
mlx_omni_server-0.5.2.dist-info/licenses/LICENSE
mlx_omni_server-0.5.2.dist-info/RECORD
