Metadata-Version: 2.4
Name: mlx-omni-server
Version: 0.5.2
Summary: MLX Omni Server is a server that provides OpenAI-compatible APIs using Apple's MLX framework.
Project-URL: Repository, https://github.com/madroidmaq/mlx-omni-server
Author-email: madroid <madroidmaq@gmail.com>
License-Expression: MIT
License-File: LICENSE
Keywords: agi,ai,aigc,mlx,openai,server,stt,tts
Classifier: Development Status :: 4 - Beta
Classifier: Intended Audience :: Developers
Classifier: Operating System :: OS Independent
Classifier: Programming Language :: Python :: 3.11
Requires-Python: >=3.11
Requires-Dist: f5-tts-mlx<0.3,>=0.2.5
Requires-Dist: fastapi<0.117,>=0.116.1
Requires-Dist: huggingface-hub>=0.30
Requires-Dist: mflux<0.14,>=0.13.0
Requires-Dist: mlx-audio>=0.2.4
Requires-Dist: mlx-embeddings>=0.0.3
Requires-Dist: mlx-lm>=0.30.0
Requires-Dist: mlx-whisper>=0.4.1
Requires-Dist: numba>=0.57.0
Requires-Dist: outlines==1.0.4
Requires-Dist: pydantic<3,>=2.9.2
Requires-Dist: python-multipart<0.0.21,>=0.0.20
Requires-Dist: rich>=13.9.4
Requires-Dist: sse-starlette<3,>=2.1.3
Requires-Dist: uvicorn<0.35,>=0.34.0
